{
    "dynasty": "唐",
    "author": "和凝",
    "location": [
        "梁洋",
        "灵泉",
        "五凤楼",
        "嵩山",
        "洛河",
        "九畴",
        "彩眉",
        "丰年",
        "神京",
        "池亭",
        "金龙",
        "井亭",
        "兰殿",
        "玉莲池",
        "黄河",
        "九曲",
        "香云",
        "金盆",
        "红兰",
        "银台",
        "凤楼",
        "金门",
        "食门",
        "帝都",
        "尧眉",
        "泰阶",
        "金殿",
        "舜弦",
        "神京",
        "尧阶",
        "含元殿",
        "越溪",
        "金井",
        "锦连乾",
        "西郊",
        "大罗",
        "兰殿",
        "金马",
        "狻猊镇",
        "金马",
        "神京",
        "乌犀",
        "曲江",
        "瓜年纪",
        "印山眉",
        "神京",
        "越王台",
        "越岭",
        "蓝水",
        "小眉",
        "洋川",
        "洋川",
        "□眉",
        "洋城",
        "灵泉",
        "巫山",
        "凤凰"
    ],
    "person": [
        "贺文明",
        "沥苏",
        "东方朔",
        "香山",
        "班定",
        "圣主",
        "班资",
        "金马",
        "尧阶",
        "舜日",
        "香莲",
        "赵飞燕",
        "阮郎",
        "姮娥",
        "潘郎",
        "支公"
    ],
    "time": [
        "清明",
        "朝元",
        "丰年"
    ]
}