{
    "dynasty": "唐",
    "author": "徐凝",
    "location": [
        "浙江",
        "东沟",
        "严陵",
        "长洲",
        "吴王",
        "长洲",
        "十二峰",
        "越溪",
        "庐山",
        "西岳",
        "白铜",
        "江南",
        "木兰",
        "江桥",
        "淮水",
        "庐山",
        "玉泉寺",
        "玉泉寺",
        "洛阳",
        "龙门",
        "洛川",
        "扬州",
        "扬州",
        "白门",
        "洛城",
        "三川",
        "五凤楼",
        "洛阳",
        "天台",
        "昭阳",
        "汉南",
        "燕支",
        "洛阳",
        "洛阳",
        "洛阳",
        "伍员庙",
        "咸京",
        "巴山",
        "锦城",
        "汴河",
        "西山",
        "玉清宫",
        "咸秦",
        "紫溪",
        "紫溪",
        "越城",
        "西川",
        "南越",
        "岭头山",
        "武夷山",
        "武夷",
        "鼎湖",
        "荆门",
        "十二峰",
        "金谷",
        "金谷",
        "和嵩阳",
        "嵩阳",
        "三十六峰",
        "瑶池",
        "嵩阳",
        "玉清眠",
        "旧山",
        "杭州",
        "沙堤",
        "钱塘",
        "剑斜",
        "木兰",
        "和川",
        "浙江",
        "浙江",
        "钱塘",
        "松溪",
        "西林",
        "小姑",
        "嵩阳",
        "岭南",
        "香炉峰",
        "香炉",
        "吴山",
        "越水",
        "长安",
        "秦王",
        "越水"
    ],
    "person": [
        "西施",
        "陶唐主",
        "乐府",
        "采莲",
        "寄潘",
        "郑女",
        "丈人",
        "丞相",
        "浙西李",
        "和侍郎",
        "苏小小",
        "孟尚书",
        "大司马",
        "蜀王",
        "夫差",
        "炀帝",
        "李补",
        "陈司马",
        "陈司马",
        "潘郎",
        "黄帝",
        "荆巫",
        "侍郎",
        "白司马",
        "白司马",
        "越施"
    ],
    "time": [
        "八月",
        "二月",
        "长庆",
        "长庆",
        "寒食",
        "八月",
        "九月",
        "八月",
        "九月",
        "八月",
        "八月",
        "八月",
        "八月"
    ]
}