{
    "dynasty": "唐",
    "author": "窦庠",
    "location": [
        "太原",
        "晋阳城",
        "洛阳",
        "金山",
        "润州",
        "金山寺",
        "西江",
        "坑谷",
        "琼楼",
        "蓬莱宫",
        "灵山",
        "金山",
        "金山",
        "灵台",
        "羊马城",
        "越（",
        "越灵嘉寺",
        "津梁",
        "灵嘉寺",
        "稽山",
        "清商",
        "荆山",
        "岳阳楼",
        "岳州",
        "巴子国",
        "谢公亭",
        "琼玉",
        "茝兰",
        "天台",
        "龙门",
        "淮南",
        "荆州",
        "金山寺",
        "东都",
        "三川",
        "崆峒",
        "庾亮楼",
        "上阳宫",
        "上阳宫"
    ],
    "person": [
        "奉和王",
        "李侍郎",
        "崔给",
        "卧龙",
        "王翰",
        "翰林王",
        "相如",
        "谢韦卿",
        "伏辕",
        "韩愈侍郎",
        "范蠡",
        "穆生陈",
        "陈蕃",
        "羊公",
        "韩仆",
        "武皇",
        "太乙"
    ],
    "time": [
        "五六"
    ]
}