{
    "dynasty": "唐",
    "author": "翁承赞",
    "location": [
        "庸门",
        "建阳",
        "建阳溪",
        "剑潭",
        "华山",
        "蒙闽王",
        "鹅子二",
        "岭湖",
        "三岛",
        "旧林泉",
        "南台",
        "蓬瀛",
        "汉皋亭",
        "雁阵",
        "洞庭",
        "长安",
        "盆池",
        "洛阳",
        "彭泽",
        "娃眉",
        "汴河",
        "秦台",
        "旧山",
        "东南",
        "岘山",
        "京洛",
        "洛阳",
        "维桑",
        "汴水",
        "长安",
        "江南",
        "华山",
        "蓬莱",
        "桂堂",
        "罗天",
        "庸楼",
        "鱼台"
    ],
    "person": [
        "文翁",
        "闽王",
        "洪崖",
        "炀帝",
        "秦娥",
        "韩信",
        "牧卧",
        "荆璞"
    ],
    "time": []
}