{
    "dynasty": "宋",
    "author": "欧阳景",
    "poems": [
        {
            "title": "句",
            "content": "清明时节正稼芳。",
            "comment": ""
        },
        {
            "title": "句",
            "content": "篇向蜀都呈巧样，被人翻入锦纹头。",
            "comment": ""
        },
        {
            "title": "兴玉泉长老",
            "content": "金鉴来觅玉泉书，金玉相逢价倍殊。到了不干藤蔓事，葫牙自去缠葫虎。",
            "comment": ""
        },
        {
            "title": "句",
            "content": "最是风流堪赏处，美人收作裛衣香。",
            "comment": ""
        }
    ]
}