{
    "dynasty": "元",
    "author": "刘因",
    "location": [
        "（王原",
        "山阳",
        "南州",
        "太行",
        "西城",
        "洛阳",
        "玉楼",
        "萨蛮湖",
        "乐府",
        "荆州",
        "廉泉",
        "（舅原",
        "西山",
        "松萝",
        "西山",
        "邯郸",
        "谢安",
        "太行",
        "黄河",
        "华胥",
        "蓬莱",
        "小桥溪",
        "长丰",
        "木兰",
        "西山",
        "木兰",
        "东皋",
        "武陵溪",
        "东山",
        "鹿门",
        "燕南",
        "三江",
        "琼楼",
        "区区",
        "沧洲",
        "白沟",
        "幽燕",
        "赵普",
        "白沟",
        "玉楼",
        "西湖",
        "江南",
        "眉宇",
        "江南",
        "降王",
        "山亭",
        "郊园",
        "太行"
    ],
    "person": [
        "张彦",
        "刘老子",
        "廉孟子",
        "贺廉侯",
        "张叟",
        "东坡",
        "山翁",
        "山翁",
        "庞公",
        "仲良",
        "丰沛"
    ],
    "time": []
}