{
    "dynasty": "元",
    "author": "张弘范",
    "location": [
        "襄阳",
        "汉江",
        "襄阳",
        "岐山",
        "池塘",
        "新丰",
        "燕山",
        "西山",
        "巫山",
        "巫阳路",
        "西湖",
        "东山",
        "武陵溪",
        "襄阳",
        "长江",
        "坚壁",
        "木兰",
        "长亭",
        "木兰",
        "木兰",
        "北海",
        "南溟",
        "铜柱",
        "玉兰",
        "龙庭",
        "木兰",
        "武津关",
        "锦江",
        "武津关",
        "虎头",
        "凤凰楼"
    ],
    "person": [
        "刘仲泽",
        "刘仲",
        "刘仲",
        "吴姬"
    ],
    "time": []
}