{
    "dynasty": "明",
    "author": "程嘉燧",
    "location": [
        "昆山",
        "江南",
        "扬州",
        "隐阁",
        "昆山",
        "九峰",
        "金陵",
        "长安",
        "县楼",
        "东林",
        "北城",
        "东林",
        "塔寺",
        "瀼滑",
        "塞垣",
        "充栋",
        "南山",
        "新丰",
        "瓜洲",
        "横江",
        "南村",
        "扬州",
        "江南",
        "北固",
        "焦岭",
        "瓜洲",
        "瓜洲",
        "周垣",
        "西湖",
        "李长",
        "旧京",
        "莲花府",
        "黄耳",
        "仲和侯",
        "西郭",
        "江南",
        "阳阿曲",
        "子薪村",
        "赵五老",
        "长源",
        "东林",
        "看焦",
        "话松",
        "锁旧",
        "长",
        "遍东",
        "将南",
        "揭翠",
        "神扬",
        "情南",
        "¤阊",
        "怀长蘅",
        "看西",
        "在西",
        "婆",
        "仍汴",
        "黄",
        "青",
        "金",
        "动翠",
        "与梁五",
        "幽",
        "潞安",
        "见并",
        "说京",
        "烛殷",
        "笑柴",
        "向京",
        "坐翠",
        "题松",
        "在西",
        "里楚",
        "归柬",
        "隔钱",
        "牵歙",
        "下西",
        "归黄",
        "莲花",
        "我天",
        "方",
        "鳞香阵",
        "皋",
        "楚",
        "望三",
        "令招",
        "问扬",
        "忆金",
        "画金",
        "过虞",
        "吴",
        "闻楚",
        "问秦",
        "岳",
        "浦",
        "汪",
        "俗殷",
        "景泰",
        "动成",
        "唐",
        "过易",
        "易",
        "云京",
        "怀长蘅",
        "客西",
        "吴",
        "我栖一",
        "与顾",
        "四",
        "汇阳庄",
        "水曹娥",
        "山贺监",
        "忆江",
        "侯",
        "江",
        "闻南",
        "雪五",
        "满长",
        "识洛",
        "金",
        "柘",
        "西",
        "逢曹",
        "在金",
        "无限",
        "上",
        "不见",
        "房响",
        "鱼",
        "欲横",
        "过拂",
        "户",
        "舍仍",
        "日泊",
        "躇",
        "道中",
        "目柬",
        "群",
        "未至",
        "）",
        "花",
        "燕南",
        "才是玉",
        "目",
        "未离黄",
        "矶吴",
        "正在九",
        "处是",
        "看舞",
        "曲赠赵",
        "字",
        "多声",
        "西湖",
        "丁卯",
        "上住",
        "有别",
        "金阊",
        "近书",
        "里青",
        "）弄",
        "澄江",
        "过三",
        "向京阙",
        "秋涨",
        "君",
        "梁园",
        "还能否",
        "空岩声",
        "束弓",
        "还归去",
        "超宗",
        "厌冰",
        "汝今",
        "生辉",
        "下",
        "暝酒",
        "水崖",
        "阶",
        "暮江",
        "蝉为",
        "皋宴",
        "郭琴",
        "清明拜",
        "半生空",
        "仲夏偶",
        "听曲",
        "名淮",
        "逢春",
        "自倭",
        "二首",
        "山中",
        "舟夜",
        "十",
        "十年",
        "¤听",
        "名",
        "兄兼",
        "多",
        "落照",
        "早春",
        "腔遍",
        "狭邪",
        "¤",
        "画钟",
        "残霙",
        "出雾",
        "歌钟何",
        "出每",
        "凭添",
        "怀季",
        "湖桥",
        "七",
        "题张",
        "舟追",
        "嵇康",
        "少雁声",
        "亭别",
        "冥冥",
        "何处",
        "含远",
        "世",
        "松傍",
        "访旧",
        "八",
        "争",
        "春"
    ],
    "person": [
        "张翁",
        "西郭",
        "陶公",
        "张卿",
        "大小",
        "张二",
        "孙二",
        "张鲁",
        "周",
        "虞卿葛",
        "牧隐",
        "和李孟",
        "庄和牧",
        "张鲁",
        "张翁",
        "故司马",
        "丘翁",
        "牧翁",
        "昭庆",
        "和牧",
        "和牧",
        "和牧",
        "孙履",
        "东林庄",
        "季康",
        "张伯",
        "和牧",
        "李长",
        "和牧",
        "寄庄",
        "谢公",
        "次孙",
        "韵和",
        "赠张",
        "张翁",
        "贾",
        "托子",
        "小",
        "韵和",
        "次宋",
        "就魏",
        "同牧",
        "儆韦",
        "同牧",
        "山庄和",
        "日张次",
        "和",
        "贾",
        "怀李",
        "怀孙履和",
        "比郑",
        "和",
        "侍",
        "当述",
        "见隆",
        "沈",
        "柴",
        "虎",
        "向生",
        "似孙",
        "徐",
        "同牧",
        "不厌",
        "微",
        "听时",
        "青",
        "赠建",
        "不深",
        "辛",
        "即事",
        "书声",
        "酬美",
        "有高",
        "夜为",
        "水想",
        "莲",
        "曲抛",
        "帘看弈",
        "谏旧",
        "月夜",
        "没思",
        "燃心",
        "朱子",
        "流水",
        "图",
        "向北",
        "堂",
        "言回",
        "寂寞向",
        "敏仲",
        "把",
        "中"
    ],
    "time": [
        "八月",
        "中秋",
        "九月",
        "五月",
        "五月",
        "画秦",
        "佳",
        "八",
        "家清",
        "花六",
        "情",
        "中",
        "清明",
        "忽开",
        "酒",
        "故交",
        "）",
        "满蕨",
        "过雨",
        "难挽",
        "灯罢",
        "经夜",
        "作",
        "失崔",
        "还往",
        "恼彻",
        "闲愁"
    ]
}