{
    "dynasty": "宋",
    "author": "俞桂",
    "location": [
        "采莲曲",
        "冷泉亭",
        "阳台",
        "采莲曲",
        "云岩",
        "占丘",
        "松江",
        "沙堤",
        "京国",
        "吴山",
        "滕阁",
        "西山",
        "翠微",
        "衡阳",
        "采莲曲",
        "平湖",
        "平湖",
        "西山",
        "京华",
        "京华",
        "杜陵",
        "东山",
        "庐山",
        "采莲曲",
        "画桥",
        "华亭",
        "惠山",
        "松关",
        "招陆",
        "西湖",
        "采莲曲",
        "采莲曲",
        "渔溪",
        "冷泉亭",
        "寓京",
        "渔溪",
        "金城",
        "金城",
        "西兴渡",
        "裴坟",
        "西山",
        "枫桥寺",
        "枫桥",
        "香林洞",
        "月月岩",
        "京国",
        "西湖",
        "渔浦",
        "西兴渡",
        "采莲曲",
        "西湖",
        "长江",
        "远寺",
        "淮南",
        "寓京",
        "白石",
        "采莲曲",
        "西湖",
        "江南",
        "南浦",
        "西湖"
    ],
    "person": [
        "虎丘",
        "吴王",
        "虎丘",
        "羲驭",
        "舒徐",
        "三公",
        "采莲",
        "桐君",
        "潘郎",
        "乐天",
        "和乐天",
        "叔祖"
    ],
    "time": [
        "清明",
        "二月",
        "清明"
    ]
}