{
    "dynasty": "宋",
    "author": "白珽",
    "location": [
        "南荒",
        "赤壁",
        "洞庭",
        "商山",
        "相国",
        "吴山",
        "里湖",
        "冷泉亭",
        "灵山",
        "灵山",
        "京洛",
        "骊山",
        "华清宫",
        "南山",
        "白鹅村",
        "门关",
        "初阳台",
        "凌云",
        "季子墓",
        "申浦",
        "禹世",
        "兰亭",
        "天竺后山",
        "长安",
        "张公洞",
        "白鹅村",
        "关门",
        "易水",
        "孔明庙",
        "玄都",
        "乌葛唐",
        "三吴",
        "凤城",
        "佛国",
        "琼圃",
        "惠山",
        "西湖",
        "里湖",
        "交河",
        "明庭",
        "西湖",
        "南屏",
        "西湖",
        "北寺",
        "六和塔",
        "龙山",
        "浮屠",
        "南纪",
        "神京",
        "帝王州",
        "楚江",
        "三岛",
        "林处士墓",
        "西湖",
        "陈柏墓",
        "中山",
        "中山",
        "河阳溪",
        "长溪",
        "长安",
        "东阁",
        "西湖",
        "南国",
        "东寺",
        "江南",
        "近茅峰",
        "江南",
        "栖霞"
    ],
    "person": [
        "苏东坡",
        "郑子真",
        "李翰",
        "谪仙",
        "桓桓周",
        "苏公",
        "词翰",
        "赵达",
        "夫鲜于",
        "子臧",
        "泰伯",
        "张公",
        "郑子真",
        "公主",
        "孔公",
        "段公",
        "朱处士",
        "燕燕",
        "林处士",
        "处士",
        "坡翁",
        "诸王",
        "后妃",
        "陈太",
        "张和",
        "府周卿",
        "张公子",
        "东林",
        "梁道士",
        "赵达",
        "夫鲜于",
        "岳武穆"
    ],
    "time": [
        "三月",
        "二月"
    ]
}