{
    "dynasty": "宋",
    "author": "祖无择",
    "location": [
        "西京",
        "幽堂",
        "曲江",
        "申申堂",
        "宋嘉",
        "乌布",
        "九日",
        "西湖",
        "西湖",
        "新州",
        "庾岭南",
        "合浦",
        "贤太守",
        "方朔",
        "北辰",
        "震山",
        "黄陂",
        "袁州",
        "南阳",
        "郓州",
        "洛阳",
        "汴水",
        "庐山",
        "曹溪",
        "泰山",
        "袁州",
        "莱州",
        "蓬莱",
        "蔡州",
        "东湖",
        "东湖",
        "庐阜",
        "庐阜",
        "方州",
        "月波楼",
        "京信",
        "班春",
        "袁州",
        "东湖",
        "袁山之阳",
        "东湖",
        "阳朔",
        "荆璧",
        "区区",
        "袁州",
        "落星寺",
        "蠡泽",
        "五湖",
        "黄石祠",
        "惠州",
        "惠州",
        "桂林",
        "汉州",
        "西湖",
        "商祚",
        "宋都",
        "张泽",
        "袁州",
        "富沙",
        "五老峰",
        "灵岩",
        "梁山",
        "禹载",
        "澶州",
        "潘华阳",
        "河阳",
        "秦川",
        "刀州",
        "京师",
        "泰山",
        "招隐",
        "疏越",
        "太守",
        "省门",
        "左麦右",
        "宣城",
        "嵩洛",
        "金陵",
        "庾岭",
        "天台",
        "颍州",
        "禹穴",
        "袁州",
        "幽池",
        "贻嘉",
        "中山",
        "州保",
        "凤台",
        "亭榭",
        "张唐",
        "剑池",
        "西山",
        "华阴",
        "灵岩",
        "石湖",
        "灵岩",
        "江州",
        "庐山",
        "乐天",
        "袁州",
        "京华",
        "亚皇坟",
        "衡阳",
        "嵇康",
        "锺嵘",
        "招台岭",
        "沃州",
        "袁州",
        "服岭",
        "云岩",
        "蒙密",
        "长沙",
        "明水",
        "陆祥院",
        "沈康",
        "吴山",
        "丰城",
        "禹门",
        "东州",
        "济南",
        "宗寺",
        "龙坂",
        "长兹",
        "江东",
        "夔龙",
        "茂庸",
        "袁州",
        "郓州",
        "波亭",
        "宋寺",
        "邛州",
        "灞陵",
        "洛阳",
        "莲房",
        "夏州",
        "桑郊",
        "南康",
        "女郎台",
        "女郎台",
        "袁州",
        "翰林",
        "袁州",
        "张寺",
        "伏招隐",
        "西峰",
        "泗水",
        "泰山",
        "日观",
        "宵凉",
        "袁州",
        "九江城",
        "涡河",
        "成都",
        "东湖",
        "太华"
    ],
    "person": [
        "莱子长",
        "卫公",
        "主公",
        "虞部",
        "禹渎",
        "牧童",
        "渐老",
        "处士",
        "贾傅",
        "司马",
        "张学士",
        "瓜时",
        "范滂",
        "贾生",
        "尧舜",
        "乐天和",
        "召公",
        "贺厦",
        "宁尔福",
        "子长",
        "陶唐",
        "达庄",
        "太康",
        "孙司",
        "谢公",
        "廉侯",
        "韩尉",
        "潘郎",
        "陶令",
        "张衡",
        "沈醉",
        "孟郊",
        "潘鬓",
        "监丞",
        "虞氏",
        "曹六",
        "子夏",
        "李苏苏",
        "刘夫子",
        "谪仙",
        "周柱",
        "鲁臧",
        "李承",
        "霍嫖姚",
        "李泰",
        "杨王孙",
        "尧典布",
        "夫子",
        "舜后",
        "宣王",
        "勾稽",
        "子真",
        "尧叟",
        "班固",
        "汉祖",
        "孟湘虞",
        "孙吴",
        "汉皇",
        "监丞",
        "乐天",
        "李虚",
        "张兟"
    ],
    "time": [
        "节明",
        "九月",
        "丰年",
        "六月",
        "五月",
        "五月"
    ]
}