{
    "dynasty": "宋",
    "author": "释明辩",
    "location": [
        "瞿昙",
        "西山",
        "龙门",
        "吕洞",
        "长江",
        "辽西",
        "黄龙头",
        "乌鸡",
        "灵山",
        "金斗峰",
        "高安滩",
        "藂林",
        "升元阁",
        "左忄右",
        "洛阳",
        "大唐",
        "黄钟宫",
        "北辰",
        "赵州",
        "马祖",
        "少林",
        "黄龙",
        "文殊",
        "龙门",
        "毗卢",
        "古寺",
        "左右",
        "口宣",
        "新丰洞"
    ],
    "person": [
        "文殊",
        "婆子",
        "子佛",
        "文殊",
        "虎头",
        "瞿昙"
    ],
    "time": []
}